examples/__init__.py
"examples/ec-multiply, compression, lot-&-sequence.py"
"examples/ec-multiply, compression, no-lot-&-sequence.py"
"examples/ec-multiply, no-compression, lot-&-sequence.py"
"examples/ec-multiply, no-compression, no-lot-&-sequence.py"
"examples/no-ec-multiply, compression.py"
"examples/no-ec-multiply, no-compression.py"
qtum_bip38/__init__.py
qtum_bip38/bip38.py
qtum_bip38/utils.py
qtum_bip38/libs/__init__.py
qtum_bip38/libs/base58.py
qtum_bip38/libs/ripemd160.py
tests/__init__.py
tests/conftest.py
tests/test_bip38.py
tests/test_utils.py
qtum_bip38-0.3.0.dist-info/LICENSE
qtum_bip38-0.3.0.dist-info/METADATA
qtum_bip38-0.3.0.dist-info/WHEEL
qtum_bip38-0.3.0.dist-info/top_level.txt
qtum_bip38-0.3.0.dist-info/RECORD
