Metadata-Version: 2.1
Name: qtum-bip38
Version: 0.3.0
Summary: Python library for implementation of BIP38 for Qtum.
Home-page: https://github.com/qtumproject/qtum-bip38
Author: Meheret Tesfaye Batu
Author-email: meherett@qtum.info
License: MIT
Project-URL: Tracker, https://github.com/qtumproject/qtum-bip38/issues
Keywords: qtum,bip38,private-key,pure-python,encrypt,decrypt,passphrase,wif,bip-0038
Classifier: Development Status :: 5 - Production/Stable
Classifier: License :: OSI Approved :: MIT License
Classifier: Programming Language :: Python :: 3.9
Classifier: Programming Language :: Python :: 3.10
Classifier: Programming Language :: Python :: 3.11
Classifier: Topic :: Software Development :: Libraries :: Python Modules
Requires-Python: >=3.9,<4
License-File: LICENSE
Requires-Dist: pyaes <2,>=1.6.1
Requires-Dist: scrypt <1,>=0.8.20
Requires-Dist: six <2,>=1.16.0
Provides-Extra: tests
Requires-Dist: pytest <8,>=7.4.0 ; extra == 'tests'
Requires-Dist: pytest-cov <5,>=4.1.0 ; extra == 'tests'
